[
  {
    "guess": "raise",
    "score": "--B-B",
    "turn": 1
  },
  {
    "guess": "utile",
    "expected_uncertainty_after_guess": 1.6308597827968234,
    "compatible": true,
    "uncertainty_before_guess": 4.523561956057013,
    "score": "--B-B",
    "turn": 2
  },
  {
    "guess": "opine",
    "expected_uncertainty_after_guess": 0.25,
    "compatible": true,
    "uncertainty_before_guess": 3,
    "score": "B-B-B",
    "turn": 3
  },
  {
    "guess": "oxide",
    "expected_uncertainty_after_guess": 0,
    "compatible": true,
    "uncertainty_before_guess": 0,
    "score": "BBBBB",
    "turn": 4
  }
]
