[
  {
    "guess": "raise",
    "score": "WW---",
    "turn": 1
  },
  {
    "guess": "crowd",
    "expected_uncertainty_after_guess": 1.9100859078448604,
    "compatible": false,
    "uncertainty_before_guess": 6.285402218862249,
    "score": "BB---",
    "turn": 2
  },
  {
    "guess": "fancy",
    "expected_uncertainty_after_guess": 0,
    "compatible": false,
    "uncertainty_before_guess": 2.321928094887362,
    "score": "-WWW-",
    "turn": 3
  },
  {
    "guess": "crank",
    "expected_uncertainty_after_guess": 0,
    "compatible": true,
    "uncertainty_before_guess": 0,
    "score": "BBBBB",
    "turn": 4
  }
]
