[
  {
    "guess": "raise",
    "score": "WW-W-",
    "turn": 1
  },
  {
    "guess": "splat",
    "expected_uncertainty_after_guess": 0.9697394274571561,
    "compatible": false,
    "uncertainty_before_guess": 4.392317422778761,
    "score": "B--W-",
    "turn": 2
  },
  {
    "guess": "duchy",
    "expected_uncertainty_after_guess": 0,
    "compatible": false,
    "uncertainty_before_guess": 2.321928094887362,
    "score": "-----",
    "turn": 3
  },
  {
    "guess": "swarm",
    "expected_uncertainty_after_guess": 0,
    "compatible": true,
    "uncertainty_before_guess": 0,
    "score": "BBBBB",
    "turn": 4
  }
]
